distend/__init__.py
distend/cli.py
distend/configuration.txt
distend/io_utils.py
distend/modifier.py
distend/serializer.py
distend-1.1.1.dist-info/LICENSE
distend-1.1.1.dist-info/METADATA
distend-1.1.1.dist-info/WHEEL
distend-1.1.1.dist-info/entry_points.txt
distend-1.1.1.dist-info/top_level.txt
distend-1.1.1.dist-info/RECORD
