Metadata-Version: 2.1
Name: distend
Version: 1.1.1
Summary: Distend - targeted word list generator
Home-page: https://github.com/not-sponsored/distend
Author: Hanwen Zuo
Author-email: HanwenZuo1@gmail.com
License: UNKNOWN
Platform: UNKNOWN
Classifier: Programming Language :: Python :: 3
Requires-Python: >=3.6
